wechatbot/__init__.py
wechatbot/bot.py
wechatbot/consts.py
wechatbot/exc.py
wechatbot/ping.py
wechatbot/run.py
wechatbot/tools.py
wechatbot-1.0.13.dist-info/DESCRIPTION.rst
wechatbot-1.0.13.dist-info/METADATA
wechatbot-1.0.13.dist-info/RECORD
wechatbot-1.0.13.dist-info/WHEEL
wechatbot-1.0.13.dist-info/entry_points.txt
wechatbot-1.0.13.dist-info/metadata.json
wechatbot-1.0.13.dist-info/top_level.txt
