Metadata-Version: 2.0
Name: wechatbot
Version: 1.0.13
Summary: a wechat bot developed for geeks
Home-page: https://github.com/chuanwu/WechatBot
Author: chuanwu
Author-email: chuanwusun@gmail.com
License: MIT
Keywords: wechat bot chatops
Platform: UNKNOWN
Requires-Dist: Pillow (==4.0.0)
Requires-Dist: anyjson (==0.3.3)
Requires-Dist: beautifulsoup4 (==4.5.1)
Requires-Dist: enum34 (==1.1.6)
Requires-Dist: gevent (==1.2.2)
Requires-Dist: pypng (==0.0.18)
Requires-Dist: pytest (==3.0.7)
Requires-Dist: qrcode (==5.3)
Requires-Dist: requests (==2.7.0)
Requires-Dist: simplejson (==3.7.3)
Requires-Dist: ujson (==1.34)
